<?xml version="1.0" encoding="utf-8"?>
<ArrayOfSettingItem xmlns:xsd="http://www.w3.org/2001/XMLSchema" xmlns:xsi="http://www.w3.org/2001/XMLSchema-instance">
  <SettingItem>
    <Name>StockSections</Name>
    <Value xsi:type="ArrayOfSectionModule">
      <SectionModule>
        <showButton>true</showButton>
        <Abbreviation>ORBT</Abbreviation>
        <EditorPositionX>710</EditorPositionX>
        <EditorPositionY>290</EditorPositionY>
        <FloatingPositionX>835</FloatingPositionX>
        <FloatingPositionY>100</FloatingPositionY>
        <showEditButton>true</showEditButton>
        <showFloatButton>true</showFloatButton>
        <IsEditorVisible>false</IsEditorVisible>
        <IsFloating>false</IsFloating>
        <IsHud>false</IsHud>
        <IsDeleted>false</IsDeleted>
        <IsHudBackground>false</IsHudBackground>
        <IsVisible>false</IsVisible>
        <LineCount>0</LineCount>
        <Name>ORBITAL</Name>
        <ReadoutModuleNames>
          <string>Orbital.ApoapsisHeight</string>
          <string>Orbital.TimeToApoapsis</string>
          <string>Miscellaneous.Separator</string>
          <string>Orbital.PeriapsisHeight</string>
          <string>Orbital.TimeToPeriapsis</string>
          <string>Miscellaneous.Separator</string>
          <string>Orbital.Eccentricity</string>
          <string>Orbital.Inclination</string>
          <string>Orbital.OrbitalPeriod</string>
          <string>Orbital.SemiMajorAxis</string>
        </ReadoutModuleNames>
      </SectionModule>
      <SectionModule>
        <showButton>true</showButton>
        <Abbreviation>SURF</Abbreviation>
        <EditorPositionX>710</EditorPositionX>
        <EditorPositionY>290</EditorPositionY>
        <FloatingPositionX>835</FloatingPositionX>
        <FloatingPositionY>100</FloatingPositionY>
        <showEditButton>true</showEditButton>
        <showFloatButton>true</showFloatButton>
        <IsEditorVisible>false</IsEditorVisible>
        <IsFloating>false</IsFloating>
        <IsHud>false</IsHud>
        <IsDeleted>false</IsDeleted>
        <IsHudBackground>false</IsHudBackground>
        <IsVisible>false</IsVisible>
        <LineCount>0</LineCount>
        <Name>SURFACE</Name>
        <ReadoutModuleNames>
          <string>Surface.AltitudeSeaLevel</string>
          <string>Surface.AltitudeTerrain</string>
          <string>Surface.Biome</string>
          <string>Miscellaneous.Separator</string>
          <string>Surface.VerticalSpeed</string>
          <string>Surface.HorizontalSpeed</string>
          <string>Miscellaneous.Separator</string>
          <string>Surface.Slope</string>
        </ReadoutModuleNames>
      </SectionModule>
      <SectionModule>
        <showButton>true</showButton>
        <Abbreviation>VESL</Abbreviation>
        <EditorPositionX>710</EditorPositionX>
        <EditorPositionY>290</EditorPositionY>
        <FloatingPositionX>835</FloatingPositionX>
        <FloatingPositionY>100</FloatingPositionY>
        <showEditButton>true</showEditButton>
        <showFloatButton>true</showFloatButton>
        <IsEditorVisible>false</IsEditorVisible>
        <IsFloating>false</IsFloating>
        <IsHud>false</IsHud>
        <IsDeleted>false</IsDeleted>
        <IsHudBackground>false</IsHudBackground>
        <IsVisible>false</IsVisible>
        <LineCount>0</LineCount>
        <Name>VESSEL</Name>
        <ReadoutModuleNames>
          <string>Vessel.Name</string>
          <string>Vessel.Mass</string>
          <string>Vessel.Gravity</string>
          <string>Miscellaneous.Separator</string>
          <string>Vessel.DeltaVStaged</string>
          <string>Vessel.DeltaVTotal</string>
          <string>Miscellaneous.Separator</string>
          <string>Vessel.ThrustToWeight</string>
          <string>Vessel.Acceleration</string>
          <string>Miscellaneous.Separator</string>
          <string>Vessel.RCSDeltaV</string>
          <string>Vessel.RCSTWR</string>
          <string>Miscellaneous.Separator</string>
          <string>Vessel.Heading</string>
          <string>Vessel.Pitch</string>
          <string>Vessel.Roll</string>
        </ReadoutModuleNames>
      </SectionModule>
      <SectionModule>
        <showButton>true</showButton>
        <Abbreviation>RDZV</Abbreviation>
        <EditorPositionX>710</EditorPositionX>
        <EditorPositionY>290</EditorPositionY>
        <FloatingPositionX>835</FloatingPositionX>
        <FloatingPositionY>100</FloatingPositionY>
        <showEditButton>true</showEditButton>
        <showFloatButton>true</showFloatButton>
        <IsEditorVisible>false</IsEditorVisible>
        <IsFloating>false</IsFloating>
        <IsHud>false</IsHud>
        <IsDeleted>false</IsDeleted>
        <IsHudBackground>false</IsHudBackground>
        <IsVisible>false</IsVisible>
        <LineCount>0</LineCount>
        <Name>RENDEZVOUS</Name>
        <ReadoutModuleNames>
          <string>Rendezvous.TargetSelector</string>
          <string>Rendezvous.PhaseAngle</string>
          <string>Rendezvous.InterceptAngle</string>
          <string>Rendezvous.TimeToTransferAngleTime</string>
          <string>Rendezvous.Distance</string>
          <string>Miscellaneous.Separator</string>
          <string>Rendezvous.TimeToRelativeAscendingNode</string>
          <string>Rendezvous.TimeToRelativeDescendingNode</string>
          <string>Rendezvous.RelativeInclination</string>
          <string>Miscellaneous.Separator</string>
          <string>Rendezvous.ApoapsisHeight</string>
          <string>Rendezvous.PeriapsisHeight</string>
          <string>Rendezvous.OrbitalPeriod</string>
          <string>Rendezvous.SemiMajorAxis</string>
        </ReadoutModuleNames>
      </SectionModule>
      <SectionModule>
        <showButton>true</showButton>
        <Abbreviation>HEAT</Abbreviation>
        <EditorPositionX>710</EditorPositionX>
        <EditorPositionY>290</EditorPositionY>
        <FloatingPositionX>835</FloatingPositionX>
        <FloatingPositionY>100</FloatingPositionY>
        <showEditButton>true</showEditButton>
        <showFloatButton>true</showFloatButton>
        <IsEditorVisible>false</IsEditorVisible>
        <IsFloating>false</IsFloating>
        <IsHud>false</IsHud>
        <IsDeleted>false</IsDeleted>
        <IsHudBackground>false</IsHudBackground>
        <IsVisible>false</IsVisible>
        <LineCount>0</LineCount>
        <Name>THERMAL</Name>
        <ReadoutModuleNames>
          <string>Thermal.InternalFlux</string>
          <string>Thermal.ConvectionFlux</string>
          <string>Thermal.RadiationFlux</string>
          <string>Thermal.CriticalPart</string>
          <string>Thermal.CriticalTemperature</string>
          <string>Thermal.CriticalSkinTemperature</string>
          <string>Thermal.CriticalThermalPercentage</string>
          <string>Thermal.HottestPart</string>
          <string>Thermal.HottestTemperature</string>
          <string>Thermal.HottestSkinTemperature</string>
          <string>Thermal.CoolestPart</string>
          <string>Thermal.CoolestTemperature</string>
          <string>Thermal.CoolestSkinTemperature</string>
        </ReadoutModuleNames>
      </SectionModule>
      <SectionModule>
        <showButton>true</showButton>
        <Abbreviation>BODY</Abbreviation>
        <EditorPositionX>710</EditorPositionX>
        <EditorPositionY>290</EditorPositionY>
        <FloatingPositionX>835</FloatingPositionX>
        <FloatingPositionY>100</FloatingPositionY>
        <showEditButton>true</showEditButton>
        <showFloatButton>true</showFloatButton>
        <IsEditorVisible>false</IsEditorVisible>
        <IsFloating>false</IsFloating>
        <IsHud>false</IsHud>
        <IsDeleted>false</IsDeleted>
        <IsHudBackground>false</IsHudBackground>
        <IsVisible>false</IsVisible>
        <LineCount>0</LineCount>
        <Name>BODY</Name>
        <ReadoutModuleNames>
          <string>Body.MinOrbitHeight</string>
          <string>Body.HighAtmosphereHeight</string>
          <string>Body.LowSpaceHeight</string>
          <string>Body.HighSpaceHeight</string>
          <string>Body.GeostationaryHeight</string>
          <string>Body.CurrentSoi</string>
          <string>Body.BodyRotationPeriod</string>
          <string>Body.BodyOrbitalPeriod</string>
          <string>Body.EscapeVelocity</string>
          <string>Body.BodyGravity</string>
        </ReadoutModuleNames>
      </SectionModule>
      <SectionModule>
        <showButton>true</showButton>
        <Abbreviation>BURN</Abbreviation>
        <EditorPositionX>710</EditorPositionX>
        <EditorPositionY>290</EditorPositionY>
        <FloatingPositionX>835</FloatingPositionX>
        <FloatingPositionY>100</FloatingPositionY>
        <showEditButton>true</showEditButton>
        <showFloatButton>true</showFloatButton>
        <IsEditorVisible>false</IsEditorVisible>
        <IsFloating>false</IsFloating>
        <IsHud>false</IsHud>
        <IsDeleted>false</IsDeleted>
        <IsHudBackground>false</IsHudBackground>
        <IsVisible>false</IsVisible>
        <LineCount>0</LineCount>
        <Name>MANEUVER</Name>
        <ReadoutModuleNames>
          <string>Orbital.NodeProgradeDeltaV</string>
          <string>Orbital.NodeNormalDeltaV</string>
          <string>Orbital.NodeRadialDeltaV</string>
          <string>Orbital.NodeTotalDeltaV</string>
          <string>Miscellaneous.Separator</string>
          <string>Orbital.NodeBurnTime</string>
          <string>Orbital.NodeTimeToHalfBurn</string>
          <string>Miscellaneous.Separator</string>
          <string>Orbital.PostBurnApoapsis</string>
          <string>Orbital.PostBurnPeriapsis</string>
          <string>Orbital.PostBurnInclination</string>
          <string>Orbital.PostBurnRealtiveInclination</string>
          <string>Orbital.PostBurnPeriod</string>
          <string>Orbital.PostBurnEccentricity</string>
        </ReadoutModuleNames>
      </SectionModule>
      <SectionModule>
        <showButton>true</showButton>
        <Abbreviation>LAND</Abbreviation>
        <EditorPositionX>710</EditorPositionX>
        <EditorPositionY>290</EditorPositionY>
        <FloatingPositionX>835</FloatingPositionX>
        <FloatingPositionY>100</FloatingPositionY>
        <showEditButton>true</showEditButton>
        <showFloatButton>true</showFloatButton>
        <IsEditorVisible>false</IsEditorVisible>
        <IsFloating>false</IsFloating>
        <IsHud>false</IsHud>
        <IsDeleted>false</IsDeleted>
        <IsHudBackground>false</IsHudBackground>
        <IsVisible>false</IsVisible>
        <LineCount>0</LineCount>
        <Name>LANDING</Name>
        <ReadoutModuleNames>
          <string>Surface.ImpactAltitude</string>
          <string>Surface.ImpactTime</string>
          <string>Surface.ImpactLatitude</string>
          <string>Surface.ImpactLongitude</string>
          <string>Surface.ImpactBiome</string>
          <string>Surface.ImpactMarker</string>
          <string>Miscellaneous.Separator</string>
          <string>Vessel.SuicideBurnAltitude</string>
          <string>Vessel.SuicideBurnDeltaV</string>
          <string>Vessel.SuicideBurnLength</string>
          <string>Vessel.SuicideBurnCountdown</string>
        </ReadoutModuleNames>
      </SectionModule>
      <SectionModule>
        <showButton>false</showButton>
        <Abbreviation>HUD 1</Abbreviation>
        <EditorPositionX>710</EditorPositionX>
        <EditorPositionY>290</EditorPositionY>
        <FloatingPositionX>518.600037</FloatingPositionX>
        <FloatingPositionY>0</FloatingPositionY>
        <showEditButton>true</showEditButton>
        <showFloatButton>true</showFloatButton>
        <IsEditorVisible>false</IsEditorVisible>
        <IsFloating>true</IsFloating>
        <IsHud>true</IsHud>
        <IsDeleted>false</IsDeleted>
        <IsHudBackground>false</IsHudBackground>
        <IsVisible>true</IsVisible>
        <LineCount>5</LineCount>
        <Name>HUD 1</Name>
        <ReadoutModuleNames>
          <string>Orbital.ApoapsisHeight</string>
          <string>Orbital.TimeToApoapsis</string>
          <string>Orbital.PeriapsisHeight</string>
          <string>Orbital.TimeToPeriapsis</string>
          <string>Miscellaneous.Separator</string>
          <string>Vessel.DeltaVCurrentTotal</string>
        </ReadoutModuleNames>
      </SectionModule>
      <SectionModule>
        <showButton>false</showButton>
        <Abbreviation>HUD 2</Abbreviation>
        <EditorPositionX>710</EditorPositionX>
        <EditorPositionY>290</EditorPositionY>
        <FloatingPositionX>1229</FloatingPositionX>
        <FloatingPositionY>0</FloatingPositionY>
        <showEditButton>true</showEditButton>
        <showFloatButton>true</showFloatButton>
        <IsEditorVisible>false</IsEditorVisible>
        <IsFloating>true</IsFloating>
        <IsHud>true</IsHud>
        <IsDeleted>false</IsDeleted>
        <IsHudBackground>false</IsHudBackground>
        <IsVisible>true</IsVisible>
        <LineCount>5</LineCount>
        <Name>HUD 2</Name>
        <ReadoutModuleNames>
          <string>Surface.AltitudeTerrain</string>
          <string>Surface.VerticalSpeed</string>
          <string>Surface.HorizontalSpeed</string>
          <string>Surface.Biome</string>
          <string>Surface.Situation</string>
        </ReadoutModuleNames>
      </SectionModule>
    </Value>
  </SettingItem>
  <SettingItem>
    <Name>CustomSections</Name>
    <Value xsi:type="ArrayOfSectionModule" />
  </SettingItem>
</ArrayOfSettingItem>